kagiapi/__init__.py
kagiapi/api.py
kagiapi/models.py
kagiapi-0.2.1.dist-info/LICENSE
kagiapi-0.2.1.dist-info/METADATA
kagiapi-0.2.1.dist-info/WHEEL
kagiapi-0.2.1.dist-info/top_level.txt
kagiapi-0.2.1.dist-info/RECORD
